RGPageRank/BaseTransformer.py
RGPageRank/DictTransformer.py
RGPageRank/DirectoryTransformer.py
RGPageRank/PageRank.py
RGPageRank/__init__.py
RGPageRank-0.0.777.dev0.dist-info/DESCRIPTION.rst
RGPageRank-0.0.777.dev0.dist-info/METADATA
RGPageRank-0.0.777.dev0.dist-info/RECORD
RGPageRank-0.0.777.dev0.dist-info/WHEEL
RGPageRank-0.0.777.dev0.dist-info/metadata.json
RGPageRank-0.0.777.dev0.dist-info/top_level.txt
