Metadata-Version: 2.0
Name: RGPageRank
Version: 0.0.777.dev
Summary: Find the most relevant information from the given collection of data.
Home-page: https://github.com/RomaGilyov/PageRank
Author: Roman Gilyov
Author-email: rgilyov@gmail.com
License: MIT
Keywords: page rank algorithm
Platform: UNKNOWN
Classifier: Development Status :: 3 - Alpha
Classifier: Intended Audience :: Developers
Classifier: Topic :: Software Development
Classifier: Programming Language :: Python :: 3
Classifier: Programming Language :: Python :: 3.3
Classifier: Programming Language :: Python :: 3.4
Classifier: Programming Language :: Python :: 3.5
Requires-Dist: matplotlib
Requires-Dist: networkx
Requires-Dist: numpy
